cscli/__init__.py
cscli/__main__.py
cscli/api_client.py
cscli/cli.py
cscli/error.py
cscli/commands/__init__.py
cscli/commands/cmd_drive.py
cscli/commands/cmd_ip.py
cscli/commands/cmd_list.py
cscli/commands/cmd_server.py
cscli/commands/cmd_vlan.py
cscli-0.7.1.dist-info/LICENSE
cscli-0.7.1.dist-info/METADATA
cscli-0.7.1.dist-info/WHEEL
cscli-0.7.1.dist-info/entry_points.txt
cscli-0.7.1.dist-info/top_level.txt
cscli-0.7.1.dist-info/RECORD
