Metadata-Version: 2.1
Name: cscli
Version: 0.7.1
Summary: CloudSigma administration CLI
Home-page: https://github.com/rstms/cscli
Author: Matt Krueger
Author-email: mkrueger@rstms.net
License: MIT license
Keywords: cscli
Platform: UNKNOWN
Classifier: Development Status :: 2 - Pre-Alpha
Classifier: Intended Audience :: Developers
Classifier: License :: OSI Approved :: MIT License
Classifier: Natural Language :: English
Classifier: Programming Language :: Python :: 3
Classifier: Programming Language :: Python :: 3.6
Classifier: Programming Language :: Python :: 3.7
Classifier: Programming Language :: Python :: 3.8
Requires-Python: >=3.6
License-File: LICENSE
Requires-Dist: Click (>=7.0)
Requires-Dist: cloudsigma (>=1.0)
Requires-Dist: PyYAML (>=5.4.1)
